{
  "/concaly/2.png": "f5RypWyG==bxofr:00-;xuIURin$00-ONMMws:x^00Mbo#^*%MNH00o$Vr-;ayIU",
  "/concaly/3.png": "f9S6Sq}vlBNY=gBP00$*k8kBxHNZ4VFqv}xHFY+}00JOxbxbJP$l00$+bXbaxGNZ",
  "/concaly/4.png": "fRKBXbay00of~pfPRjj@ayjsayay9ZkC%MjuM{ayRjfkfPj[j[j[D%j?%LjsNGay",
  "/concaly/5.png": "fMKx9%a~00oc~qawM{kBj?jaa#ay0KoJ?ba#D%j]M{jYj[kCj=kC9ZkC%MayM|f6",
  "/concaly/6.png": "f7SPR#oj?t%C.Ar;00s=tPt3kWoe00$_R8V~aIg400xTV^kFr;bw00t8x@t5bJWA",
  "/concaly/header.png": "f6Rfd].A4.~p?wrp00t6oIR+IU%L00rq-pWrxVIq00xWtRt6V@oz00n$xaV@Rjoe",
  "/concaly-logo.png": "f8T7}]yED4vJENyZxBemf,gPf,emDNeRE.caEmZzxZg5bceRelfkDNf,F~aID$bc",
  "/inquiryon-logo.png": "fD7pulo~8wt-VYL#adQ,aKt,o}o}HXL}tmyst,V@ayystmL}VsV@L}u5yYQlaeae",
  "/jonadrew/10-2 try 2.webp": "fEFr-HRQ?^WA$$-U_MniIqt7RPofIptR#+R5s:NHx]W=$erqOEt7t7V@M{soWBX8",
  "/jonadrew/10-2.webp": "fHFY=CM|.kNGoc$%_LsSR,t7eUkC9vxtrsRPbZNHb^bcs9nOOEozozWBM|j[RkWq",
  "/jonadrew/4-26.webp": "fiMGx8_N?wxaxuIU%g%Mf+M{M{RPxuIUxtIUt7t7j[kCa#oeoeWCS$o0t6R*WBbb",
  "/jonadrew/4-26b.webp": "fsO:R..8?^IU%MRj%1WCRkt7WBjZ%#afV@RPV@fkx]M{ofoKV[ofR+jsV?ozozof",
  "/jonadrew/4-26c.webp": "fhP6s-.7_NIo-;M{WqMxxubIWWxu.9R*MxoLRjt7t7t7R*s:adRj%gWBRjoefka}",
  "/jonadrew/9-25.webp": "fSM7V[oeo$xut8ay~pazRkoLV@WBx^j[RiRjRjofIUf6oeWBozofs:WXR*ocofWV",
  "/jonadrew/9-26.webp": "f9L;d7-o~W%Mj[jZ~pE1R*WBt7xu-:%LD*M{WBRj%MaeM{xuRjRjxtWBj]M{xut7",
  "/jonadrew/9-26b.webp": "fAJ7R500Lg9wKP#k9Z~B9aO@s.r=0R-;#8%1#kOY4oE*-o#7S5tRMwbvr=IVOZM|",
  "/jonadrew/9-26c.webp": "fRLz${IUK-t8xYs+W9NGa~Rjt7t7KSs,xAf,V?ofX9jYoLR+n~t6I]WXr;s+WBWB",
  "/jonadrew/9-26e.webp": "f8IqS@0K00-n00g*0MbvIUoM%#r;00-:xrNf_NVW=rWYyYnMm+XU00Wr%#a0#kbv",
  "/jonadrew/9-26f.webp": "fCJHXCo#5ubbS~w]00jroaWCRls.CToL+?adn5SOxTaytAxa%KNIQ-t7SzWXS4af",
  "/jonadrew/9-26g.webp": "f8IX{XNeP;RRzUnhvyV[TejbrXn~L2nhquxYk=bICSxCvLs,bba#D+skxtozRkbb",
  "/jonadrew/9-26h.webp": "fBH_e|t7pdIVnMt8_NM|Z$WBV@oz00xuRPofWYt6t7xuxuNGozadyDIUnOWBozWC",
  "/jonadrew/9-27b copy.webp": "f7G@uyi|T1kVeTR*~CWC5lazwIR*|2ELS1-WSejZ1HofnOIobv$*XTxH=KW-o#oL",
  "/jonadrew/header.webp": "fGI=Jaoz^+IV?bof59M{IUxt-;Rj~pIUDjofM{t7-;ofs:M{D%t7t8t7f6Rjaxay",
  "/mudboard/0.png": "fOKB2UIWIAIURhM_?wNHi^RORiax-;WAR,f5nin%~pMxIUogR,a#?bj=NGWBjvj]",
  "/mudboard/2.png": "fJHo2gMe00?HRQ~p%2RjRjt7WBj[M{t7t7WVxtRjj]ayRjj[ayWBIUt7%LayofWB",
  "/mudboard/3.png": "f6LXDD000000004o00~qbD?vNFD%00W--;%M.8%g00sp.9Ip?b?G00M{%gV[?b.8",
  "/mudboard/4.png": "fKNwNDIn00009GR7.8IUoLo0RPj]DP_4D%M{%eNYIAxubEW:bbWTD%-;RiV@t8WF",
  "/mudboard/5.png": "f2Fr9YRp8yRkT[nl.7ohJOV[s.aM4UxH*GnQv,nmJ|My~XxbcWs;TuM}Q:nPt*nl",
  "/mudboard/header.png": "fUMjw69F9GIAM{RPMxxvWAWUt6W.?^RiRjV@RPxa-;MxoLkCWURj-;WAWUa#bIRk",
  "/mudboard-logo.png": "fFI}O{IU00x]4n.8oft7j[t7RjIA00WB_Nj[xuRjRjIUWBoft7.8oft7Rjayx]M{",
  "/pct/1.webp": "fkEzs8t8niozofW;.At6ofkDjZofxts-jtkCaxof%MofaekCj[ayxvoJjsW;WBf5",
  "/pct/2.webp": "fsEzTaRRs,j[f5a}yGRPoIayjrayxvV@oJaya#j@t7R-t6j[kCf6kEogofWBaxay",
  "/pct/3.webp": "fQL;v--=DiNIxtogE3xaM|Rlt6og?wxtt8NHt6RjtSWAogRkWAj[M{RjbIRiayWB",
  "/pct/4.webp": "fzF?bDxaaej]W=j[.TjZfPR,W=oeEmR*ofR+oKj[NfW=kCt5n~WCaej[ofs,WBj?",
  "/pct/5.webp": "fCIzn;}?0*S5Wpj?s[R:$~ocWVWD01EN=ss+s.oL.6$xIqj[sms.adRkWWjYRlWE",
  "/pct/6.webp": "fZJkyBNLZ~floextT#RjaJaeRjj]tSM{WBadoKbIJCxZaeM|V[WBtmxaRPbIWBax",
  "/pct/7.webp": "fkI=VrtSRjjZbEa|%%Sjf4j?WCoLK8f,aeWDoea{XUNHjYt6oea#SiRifikCWCj[",
  "/pct/8.webp": "fiHVq]xts:oLV[oz-@n%s:axj[WCtmt6s:RjofWBR:ofR%WBayWVW:RjWBofWBa#",
  "/pct/9.webp": "fkGv3R9EWBWVofWB_4RjWBflayfPR.xuogflbHaxR.oLt7kCa}f6WYj[ofofj]j[",
  "/pct/IMG_5756.webp": "ffK-F5%1IB%2IUIU?wkCRjogWAM{jZR+a}aekCWBRjjZofj[ofj[xaa|ayj[WVjZ",
  "/pct/IMG_5933.webp": "fbIOUrR4RPbIR*jZ_NM|V@j[R*WC-;bcWCo1j@aytRWrs:oeaya#xuR-oet6oLof",
  "/pct/header.webp": "fpIrNRRjslNIocay~qR.obWCa{WCx[bcj[oKj[ayozayjuoLj[oLW?axa|oeWVbH",
  "/pct/sample2.jpg": "fZKxe=aKT0s9tlj=yGNGoznONeoeD$R-WAxCRnxa%2NIRlRkNGofbEWBt5xZS5bI"
}